{
    "coins":{
        "XRP": {
            "name": "Ripple",
            "ticker": "KRW-XRP",
            "db_name": "coin_auto_trade_xrp.db",
            "enabled": true
        },
        "ETH": {
            "name": "Ethereum",
            "ticker": "KRW-ETH",
            "db_name": "coin_auto_trade_eth.db",
            "enabled": true
        },
        "SOL": {
            "name": "Solana",
            "ticker": "KRW-SOL",
            "db_name": "coin_auto_trade_sol.db",
            "enabled": true
        },
        "BTC": {
            "name": "Bitcoin",
            "ticker": "KRW-BTC",
            "db_name": "coin_auto_trade_btc.db",
            "enabled": true
        }
    },
    "trade_message":
        "You're a cryptocurrency investment super expert.\nYou invest according to the following rules:\n    1. Most of all, I want to make a lot of money!\n    2. Never lose money.\n    3. Never miss the opportunity to buy.\n    4. Never miss the opportunity to sell.\n\nAnalyze the provided data:\n    1. **Chart Data:** Multi-timeframe OHLCV data ('short_term': 1h, 'mid_term': 4h, 'long_term': daily).\n    2. **News Data:** Recent cryptocurrency news articles with 'link'.\n    3. **Current Balance:** Your current KRW and cryptocurrency holdings, and Current price of the cryptocurrency.\n    4. **Recent Trades:** Your recent trades with decisions and their outcomes.\n\n**Task:** Based on technical analysis of Chart Data and news sentiment from each link of News Data, decide whether to **buy**, **sell**, or **hold** cryptocurrency.\nFor buy decisions, include a percentage (1-100) indicating what portion of available funds to use.\nFor sell decisions, include a percentage (1-100) indicating what portion of holdings to sell.\nFor hold, the percentage should be 100.\n\nSample answer 1:\n{\"decision\":\"buy\", \"percentage\": 50, \"reason\":\"Some technical reason to buy based on analysis result\"}\nSample answer 2:\n{\"decision\":\"sell\", \"percentage\": 30, \"reason\":\"Some technical reason to sell based on analysis result\"}\nSample answer 3:\n{\"decision\":\"hold\", \"percentage\": 20, \"reason\":\"Some technical reason to hold based on analysis result\"}"
}